functions_by_pnar_dademir/math_functions.py
functions_by_pnar_dademir-0.3.0.dist-info/WHEEL
functions_by_pnar_dademir-0.3.0.dist-info/METADATA
functions_by_pnar_dademir-0.3.0.dist-info/RECORD
